{
  "catalogue": {
    "bocchi": {
      "name": [
        "Guitar, Loneliness and Blue Planet",
        "If I could be a constellation",
        "Never forget",
        "That band",
        "Into the Light"
      ],
      "background": ["#4C2633", "#4C2633", "#59420E", "#0C3958", "#4E441A"],
      "text": ["#ED709A", "#e81a5b", "#f6b31a", "#1a7cc3", "#f6b31a"]
    },
    "daily": {
      "book": [
        {
          "name": "Mondstadt",
          "label": [],
          "character": [
            [
              "Aloy",
              "Amber",
              "Barbara",
              "Diona",
              "Klee",
              "Sucrose",
              "Tartaglia"
            ],
            ["Bennett", "Diluc", "Eula", "Jean", "Mona", "Noelle", "Razor"],
            ["Albedo", "Fischl", "Kaeya", "Lisa", "Rosaria", "Venti"]
          ]
        },
        {
          "name": "Liyue",
          "label": [],
          "character": [
            ["Keqing", "Ningguang", "Qiqi", "Shenhe", "Xiao", "Yelan"],
            ["Chongyun", "Ganyu", "Hu Tao", "Kazuha", "Xiangling", "Yun Jin"],
            ["Beidou", "Xingqui", "Xinyan", "Yanfei", "Zhongli"]
          ]
        },
        {
          "name": "Inazuma",
          "label": [],
          "character": [
            ["Kokomi", "Heizou", "Thoma", "Yoimiya"],
            ["Ayaka", "Itto", "Ayato", "Kujou Sara", "Shinobu"],
            ["Gorou", "Raiden", "Sayu", "Yae Miko"]
          ]
        },
        {
          "name": "Sumeru",
          "label": [],
          "character": [
            ["Candace", "Cyno", "Faruzan", "Tighnari"],
            ["Alhaitham", "Dori", "Layla", "Nahida"],
            ["Collei", "Nilou", "Wanderer", "Dehya"]
          ]
        }
      ],
      "weapon": {}
    },
    "genshin_songs": [
      {
        "name": "A Glorious Awakening",
        "sub": "Kokomi"
      },
      {
        "name": "Shirasagi Princess",
        "sub": "Ayaka"
      },
      {
        "name": "Let's Go, Crimson Knight!",
        "sub": "Klee"
      },
      {
        "name": "Termination of Desires",
        "sub": "Raiden"
      },
      {
        "name": "Path of Yaksha",
        "sub": "Xiao"
      },
      {
        "name": "Rex Incognito",
        "sub": "Zhongli"
      },
      {
        "name": "Qilin's Prance",
        "sub": "Ganyu"
      },
      {
        "name": "Any Last Words",
        "sub": "Hu Tao"
      },
      {
        "name": "Dance of Aphros",
        "sub": "Eula"
      }
    ],
    "bgData": [
      "template_1.png",
      "wallpaper-default.jpg",
      "template_2.png",
      "template_3.jpeg",
      "template_4.jpg"
    ],
    "bgColor": ["14,47,89", "31,54,96", "0,40,68", "58,60,90", "54, 26, 115"],
    "genshinText": ["#5c8eaf", "#ffebd5", "#b7b4d6", "#F2AEC1", "#D773D9"],
    "genshinSubText": ["#b2d1ea", "#aa9cc9", "#ebe2ef", "#849EBF", "#E0B6F2"]
  }
}
